MANIFEST.in
README.rst
setup.py
collective/.DS_Store
collective/__init__.py
collective/__init__.pyc
collective.ptg.simplegallery.egg-info/PKG-INFO
collective.ptg.simplegallery.egg-info/SOURCES.txt
collective.ptg.simplegallery.egg-info/dependency_links.txt
collective.ptg.simplegallery.egg-info/entry_points.txt
collective.ptg.simplegallery.egg-info/namespace_packages.txt
collective.ptg.simplegallery.egg-info/not-zip-safe
collective.ptg.simplegallery.egg-info/requires.txt
collective.ptg.simplegallery.egg-info/top_level.txt
collective/ptg/.DS_Store
collective/ptg/__init__.py
collective/ptg/__init__.pyc
collective/ptg/simplegallery/.DS_Store
collective/ptg/simplegallery/__init__.py
collective/ptg/simplegallery/__init__.pyc
collective/ptg/simplegallery/configure.zcml
collective/ptg/simplegallery/i18n.sh
collective/ptg/simplegallery/simplegallery.pt
collective/ptg/simplegallery/locales/.DS_Store
collective/ptg/simplegallery/locales/collective.ptg.simplegallery.pot
collective/ptg/simplegallery/locales/en/.DS_Store
collective/ptg/simplegallery/locales/en/LC_MESSAGES/.DS_Store
collective/ptg/simplegallery/locales/en/LC_MESSAGES/collective.ptg.simplegallery.mo
collective/ptg/simplegallery/locales/en/LC_MESSAGES/collective.ptg.simplegallery.po
collective/ptg/simplegallery/locales/no/LC_MESSAGES/.DS_Store
collective/ptg/simplegallery/locales/no/LC_MESSAGES/collective.ptg.simplegallery.mo
collective/ptg/simplegallery/locales/no/LC_MESSAGES/collective.ptg.simplegallery.po
collective/ptg/simplegallery/resources/no_style.css
collective/ptg/simplegallery/resources/shadow.css
collective/ptg/simplegallery/resources/small.css
collective/ptg/simplegallery/resources/style.css
collective/ptg/simplegallery/resources/underline.css
collective/ptg/simplegallery/resources/underlineII.css
docs/HISTORY.txt
docs/INSTALL.txt
docs/LICENSE.GPL
docs/LICENSE.txt